[
  {
    "index": 1,
    "fullSentence": "친구에게 연필 두 자루를 빌렸다",
    "sentences": ["친구에게", "연필", "두", "자루를", "빌렸다"],
    "keyword": ["친구", "연필", "두", "자루", "빌렸다"]
  },
  {
    "index": 2,
    "fullSentence": "사촌 언니는 키가 크고 날씬하다",
    "sentences": ["사촌", "언니는", "키가", "크고", "날씬하다"],
    "keyword": ["사촌", "언니", "키", "크고", "날씬하다"]
  },
  {
    "index": 3,
    "fullSentence": "사진을 보니 어린 시절이 생각난다",
    "sentences": ["사진을", "보니", "어린", "시절이", "생각난다"],
    "keyword": ["사진", "보니", "어린", "시절", "생각난다"]
  },
  {
    "index": 4,
    "fullSentence": "비가 많이 와서 옷이 다 젖었다",
    "sentences": ["비가", "많이 와서", "옷이", "다", "젖었다"],
    "keyword": ["비", "많이", "옷", "다", "젖었다"]
  },
  {
    "index": 5,
    "fullSentence": "내 친구는 노란색 치마를 입었다",
    "sentences": ["내", "친구는", "노란색", "치마를", "입었다"],
    "keyword": ["내", "친구", "노란색", "치마", "입었다"]
  },
  {
    "index": 6,
    "fullSentence": "따뜻한 봄이 빨리 오면 좋겠다",
    "sentences": ["따뜻한", "봄이", "빨리", "오면", "좋겠다"],
    "keyword": ["따뜻한", "봄", "빨리", "오면", "좋겠다"]
  },
  {
    "index": 7,
    "fullSentence": "사람이 많아서 앉을 자리가 없다",
    "sentences": ["사람이", "많아서", "앉을", "자리가", "없다"],
    "keyword": ["사람", "많아", "앉을", "자리", "없다"]
  },
  {
    "index": 8,
    "fullSentence": "눈이 내려서 산의 모습이 아름답다",
    "sentences": ["눈이", "내려서", "산의", "모습이", "아름답다"],
    "keyword": ["눈", "내려", "산", "모습", "아름답다"]
  },
  {
    "index": 9,
    "fullSentence": "추운 겨울에 먹는 호떡이 맛있다",
    "sentences": ["추운", "겨울에", "먹는", "호떡이", "맛있다"],
    "keyword": ["추운", "겨울", "먹는", "호떡", "맛있다"]
  },
  {
    "index": 10,
    "fullSentence": "내일 기차를 타고 휴가를 갔다",
    "sentences": ["내일", "기차를", "타고", "휴가를", "갔다"],
    "keyword": ["내일", "기차", "타고", "휴가", "갔다"]
  },
  {
    "index": 11,
    "fullSentence": "약속한 시간에 도착하려면 빨리 출발하자",
    "sentences": ["약속한", "시간에", "도착하려면", "빨리", "출발하자"],
    "keyword": ["약속한", "시간", "도착", "빨리", "출발하자"]
  },
  {
    "index": 12,
    "fullSentence": "서울에서 중요한 행사가 열릴 예정이다",
    "sentences": ["서울에서", "중요한", "행사가", "열릴", "예정이다"],
    "keyword": ["서울", "중요한", "행사", "열릴", "예정이다"]
  },
  {
    "index": 13,
    "fullSentence": "바깥 날씨도 좋은데 밖으로 나가자",
    "sentences": ["바깥", "날씨도", "좋은데", "밖으로", "나가자"],
    "keyword": ["바깥", "날씨", "좋은데", "밖", "나가자"]
  },
  {
    "index": 14,
    "fullSentence": "남동생은 노란색 셔츠와 청바지를 입고있다",
    "sentences": ["남동생은", "노란색", "셔츠와", "청바지를", "입고있다"],
    "keyword": ["남동생", "노란색", "셔츠", "청바지", "입고있다"]
  },
  {
    "index": 15,
    "fullSentence": "관광도 하고 맛있는 음식도 먹자",
    "sentences": ["관광도", "하고", "맛있는", "음식도", "먹자"],
    "keyword": ["관광", "하고", "맛있는", "음식", "먹자"]
  },
  {
    "index": 16,
    "fullSentence": "일찍 학교에 가니 아무도 없었다",
    "sentences": ["일찍", "학교에", "가니", "아무도", "없었다"],
    "keyword": ["일찍", "학교", "가니", "아무도", "없었다"]
  },
  {
    "index": 17,
    "fullSentence": "친구에게 편지를 보냈는데 답장이 왔다",
    "sentences": ["친구에게", "편지를", "보냈는데", "답장이", "왔다"],
    "keyword": ["친구", "편지", "보냈는데", "답장", "왔다"]
  },
  {
    "index": 18,
    "fullSentence": "목도리를 사고 싶었지만 비싸서 못 샀다",
    "sentences": ["목도리를", "사고", "싶었지만", "비싸서", "못 샀다"],
    "keyword": ["목도리", "사고", "싶었지만", "비싸서", "못 샀다"]
  },
  {
    "index": 19,
    "fullSentence": "시장에서 고기와 여러가지 과일을 샀습니다",
    "sentences": ["시장에서", "고기와", "여러가지", "과일을", "샀습니다"],
    "keyword": ["시장", "고기", "여러가지", "과일", "샀습니다"]
  },
  {
    "index": 20,
    "fullSentence": "매일 아침 어머니는 도시락을 준비하신다",
    "sentences": ["매일", "아침", "어머니는", "도시락을", "준비하신다"],
    "keyword": ["매일", "아침", "어머니", "도시락", "준비하신다"]
  },
  {
    "index": 21,
    "fullSentence": "길이 막히지 않아서 빨리 도착했다",
    "sentences": ["길이", "막히지", "않아서", "빨리", "도착했다"],
    "keyword": ["길", "막히지", "않아", "빨리", "도착했다"]
  },
  {
    "index": 22,
    "fullSentence": "모든 학생은 박물관 입장이 무료이다",
    "sentences": ["모든", "학생은", "박물관", "입장이", "무료이다"],
    "keyword": ["모든", "학생", "박물관", "입장", "무료이다"]
  },
  {
    "index": 23,
    "fullSentence": "일주일에 한 번 아빠랑 목욕탕에 간다",
    "sentences": ["일주일에", "한 번", "아빠랑", "목욕탕에", "간다"],
    "keyword": ["일주일", "한 번", "아빠", "목욕탕", "간다"]
  },
  {
    "index": 24,
    "fullSentence": "가족들과 식당에 가서 밥을 먹었다",
    "sentences": ["가족들과", "식당에", "가서", "밥을", "먹었다"],
    "keyword": ["가족들", "식당", "가서", "밥", "먹었다"]
  },
  {
    "index": 25,
    "fullSentence": "저녁에 산책을 하면서 사진을 찍었다",
    "sentences": ["저녁에", "산책을", "하면서", "사진을", "찍었다"],
    "keyword": ["저녁", "산책", "하면서", "사진", "찍었다"]
  },
  {
    "index": 26,
    "fullSentence": "쓴맛을 싫어서 커피에 설탕을 넣었다",
    "sentences": ["쓴맛이", "싫어서", "커피에", "설탕을", "넣었다"],
    "keyword": ["쓴맛", "싫어", "커피", "설탕", "넣었다"]
  },
  {
    "index": 27,
    "fullSentence": "안개가 심한 날은 조심히 운전해라",
    "sentences": ["안개가", "심한", "날은", "조심히", "운전해라"],
    "keyword": ["안개", "심한", "날", "조심히", "운전해라"]
  },
  {
    "index": 28,
    "fullSentence": "냄비에 마늘과 양파를 넣고 볶아라",
    "sentences": ["냄비에", "마늘과", "양파를", "넣고", "볶아라"],
    "keyword": ["냄비", "마늘", "양파", "넣고", "볶아라"]
  },
  {
    "index": 29,
    "fullSentence": "관광지에 가서 가족사진을 많이 찍었다",
    "sentences": ["관광지에", "가서", "가족사진을", "많이", "찍었다"],
    "keyword": ["관광지", "가서", "가족사진", "많이", "찍었다"]
  },
  {
    "index": 30,
    "fullSentence": "오전에 운동를 하고 샤워를 했다",
    "sentences": ["오전에", "운동를", "하고", "샤워를", "했다"],
    "keyword": ["오전", "운동", "하고", "샤워", "했다"]
  },
  {
    "index": 31,
    "fullSentence": "빵집 앞에서 맛있는 냄새가 났다",
    "sentences": ["빵집", "앞에서", "맛있는", "냄새가", "났다"],
    "keyword": ["빵집", "앞", "맛있는", "냄새", "났다"]
  },
  {
    "index": 32,
    "fullSentence": "언니는 얼굴도 예쁘고 마음도 착하다",
    "sentences": ["언니는", "얼굴도", "예쁘고", "마음도", "착하다"],
    "keyword": ["언니", "얼굴", "예쁘고", "마음", "착하다"]
  },
  {
    "index": 33,
    "fullSentence": "백화점에 귀여운 아기 옷이 많다",
    "sentences": ["백화점에", "귀여운", "아기", "옷이", "많다"],
    "keyword": ["백화점", "귀여운", "아기", "옷", "많다"]
  },
  {
    "index": 34,
    "fullSentence": "동생이 연못에서 개구리 두 마리를 잡았다",
    "sentences": ["동생이", "연못에서", "개구리", "두 마리를", "잡았다"],
    "keyword": ["동생", "연못", "개구리", "두 마리", "잡았다"]
  },
  {
    "index": 35,
    "fullSentence": "도시에는 자동차가 많아서 공기가 탁하다",
    "sentences": ["도시에는", "자동차가", "많아서", "공기가", "탁하다"],
    "keyword": ["도시", "자동차", "많아", "공기", "탁하다"]
  },
  {
    "index": 36,
    "fullSentence": "많은 사람들이 공원에서 운동을 한다",
    "sentences": ["많은", "사람들이", "공원에서", "운동을", "한다"],
    "keyword": ["많은", "사람들", "공원", "운동", "한다"]
  },
  {
    "index": 37,
    "fullSentence": "점심에 친구랑 튀김과 김밥을 먹었다",
    "sentences": ["점심에", "친구랑", "튀김과", "김밥을", "먹었다"],
    "keyword": ["점심", "친구", "튀김", "김밥", "먹었다"]
  },
  {
    "index": 38,
    "fullSentence": "주말마다 운동장에서 친구들과 축구를 한다",
    "sentences": ["주말마다", "운동장에서", "친구들과", "축구를", "한다"],
    "keyword": ["주말", "운동장", "친구들", "축구", "한다"]
  },
  {
    "index": 39,
    "fullSentence": "아침 일찍 일어나 체조를 한다",
    "sentences": ["아침", "일찍", "일어나", "체조를", "한다"],
    "keyword": ["아침", "일찍", "일어나", "체조", "한다"]
  },
  {
    "index": 40,
    "fullSentence": "요즘 날씨가 더워서 에어컨이 필요하다",
    "sentences": ["요즘", "날씨가", "더워서", "에어컨이", "필요하다"],
    "keyword": ["요즘", "날씨", "더워", "에어컨", "필요하다"]
  },
  {
    "index": 41,
    "fullSentence": "냄비에 물과 미역을 넣고 끓이세요",
    "sentences": ["냄비에", "물과", "미역을", "넣고", "끓이세요"],
    "keyword": ["냄비", "물", "미역", "넣고", "끓이세요"]
  },
  {
    "index": 42,
    "fullSentence": "아침에 커피를 마시며 하루를 시작한다",
    "sentences": ["아침에", "커피를", "마시며", "하루를", "시작한다"],
    "keyword": ["아침", "커피", "마시며", "하루", "시작한다"]
  },
  {
    "index": 43,
    "fullSentence": "태풍이 와서 집이 날아갈 뻔했다",
    "sentences": ["태풍이", "와서", "집이", "날아갈", "뻔했다"],
    "keyword": ["태풍", "와서", "집", "날아갈", "뻔했다"]
  },
  {
    "index": 44,
    "fullSentence": "학생들이 선생님과 교실 안으로 들어갔다",
    "sentences": ["학생들이", "선생님과", "교실", "안으로", "들어갔다"],
    "keyword": ["학생들", "선생님", "교실", "안으로", "들어갔다"]
  },
  {
    "index": 45,
    "fullSentence": "아이는 잠자기 전에 책을 읽는다",
    "sentences": ["아이는", "잠자기", "전에", "책을", "읽는다"],
    "keyword": ["아이", "잠자기", "전", "책", "읽는다"]
  },
  {
    "index": 46,
    "fullSentence": "여행에 가서 편한 옷을 입었다",
    "sentences": ["여행에", "가서", "편한", "옷을", "입었다"],
    "keyword": ["여행", "가서", "편한", "옷", "입었다"]
  },
  {
    "index": 47,
    "fullSentence": "엄마는 무릎이 아파서 병원에 갔다",
    "sentences": ["엄마는", "무릎이", "아파서", "병원에", "갔다"],
    "keyword": ["엄마", "무릎", "아파", "병원", "갔다"]
  },
  {
    "index": 48,
    "fullSentence": "평소에 회사에서 무슨 일을 하세요",
    "sentences": ["평소에", "회사에서", "무슨", "일을", "하세요"],
    "keyword": ["평소", "회사", "무슨", "일", "하세요"]
  },
  {
    "index": 49,
    "fullSentence": "도시락을 싸서 공원으로 소풍을 갔다",
    "sentences": ["도시락을", "싸서", "공원으로", "소풍을", "갔다"],
    "keyword": ["도시락", "싸서", "공원", "소풍", "갔다"]
  },
  {
    "index": 50,
    "fullSentence": "아침에 잠을 자고 있는 동생을 깨웠다",
    "sentences": ["아침에", "잠을", "자고 있는", "동생을", "깨웠다"],
    "keyword": ["아침", "잠", "자고 있는", "동생", "깨웠다"]
  },
  {
    "index": 51,
    "fullSentence": "친척을 만나러 오랜만에 시골에 갔다",
    "sentences": ["친척을", "만나러", "오랜만에", "시골에", "갔다"],
    "keyword": ["친척", "만나", "오랜만에", "시골", "갔다"]
  },
  {
    "index": 52,
    "fullSentence": "지하철에서 오 분 거리에 박물관이 있다",
    "sentences": ["지하철에서", "오 분", "거리에", "박물관이", "있다"],
    "keyword": ["지하철", "오 분", "거리", "박물관", "있다"]
  },
  {
    "index": 53,
    "fullSentence": "입학 기념으로 새로운 책가방을 샀다",
    "sentences": ["입학", "기념으로", "새로운", "책가방을", "샀다"],
    "keyword": ["입학", "기념", "새로운", "책가방", "샀다"]
  },
  {
    "index": 54,
    "fullSentence": "가을에는 나뭇잎이 붉게 물들어서 예쁘다",
    "sentences": ["가을에는", "나뭇잎이", "붉게", "물들어서", "예쁘다"],
    "keyword": ["가을", "나뭇잎", "붉게", "물들어", "예쁘다"]
  },
  {
    "index": 55,
    "fullSentence": "주말에는 가족들과 마트에서 장을 보았다",
    "sentences": ["주말에는", "가족들과", "마트에서", "장을", "보았다"],
    "keyword": ["주말", "가족들", "마트", "장", "보았다"]
  },
  {
    "index": 56,
    "fullSentence": "대회에서 상을 받아 매우 기쁘다",
    "sentences": ["대회에서", "상을", "받아", "매우", "기쁘다"],
    "keyword": ["대회", "상", "받아", "매우", "기쁘다"]
  },
  {
    "index": 57,
    "fullSentence": "배가 너무 불러서 음식을 남겼다",
    "sentences": ["배가", "너무", "불러서", "음식을", "남겼다"],
    "keyword": ["배", "너무", "불러", "음식", "남겼다"]
  },
  {
    "index": 58,
    "fullSentence": "친구를 만나러 학교에 가는 중이다",
    "sentences": ["친구를", "만나러", "학교에", "가는", "중이다"],
    "keyword": ["친구", "만나러", "학교", "가는", "중이다"]
  },
  {
    "index": 59,
    "fullSentence": "명절에 준비한 반찬이 많이 남았다",
    "sentences": ["명절에", "준비한", "반찬이", "많이", "남았다"],
    "keyword": ["명절", "준비", "반찬", "많이", "남았다"]
  },
  {
    "index": 60,
    "fullSentence": "비행기 표를 상당히 싸게 예매했다",
    "sentences": ["비행기", "표를", "상당히", "싸게", "예매했다"],
    "keyword": ["비행기", "표", "상당히", "싸게", "예매했다"]
  },
  {
    "index": 61,
    "fullSentence": "주말에 삼촌의 카메라를 잠깐 빌렸다",
    "sentences": ["주말에", "삼촌의", "카메라를", "잠깐", "빌렸다"],
    "keyword": ["주말", "삼촌", "카메라", "잠깐", "빌렸다"]
  },
  {
    "index": 62,
    "fullSentence": "밤에는 게임을 하거나 음악을 듣는다",
    "sentences": ["밤에는", "게임을", "하거나", "음악을", "듣는다"],
    "keyword": ["밤", "게임", "하거나", "음악", "듣는다"]
  },
  {
    "index": 63,
    "fullSentence": "지금 국수를 먹으러 가는 길이다",
    "sentences": ["지금", "국수를", "먹으러", "가는", "길이다"],
    "keyword": ["지금", "국수", "먹으러", "가는", "길이다"]
  },
  {
    "index": 64,
    "fullSentence": "화장실에 다녀온 사이에 전화가 왔다",
    "sentences": ["화장실에", "다녀온", "사이에", "전화가", "왔다"],
    "keyword": ["화장실", "다녀온", "사이", "전화", "왔다"]
  },
  {
    "index": 65,
    "fullSentence": "다리를 다쳐서 병원에 입원을 했다",
    "sentences": ["다리를", "다쳐서", "병원에", "입원을", "했다"],
    "keyword": ["다리", "다쳐서", "병원", "입원", "했다"]
  },
  {
    "index": 66,
    "fullSentence": "현관문 앞에 커다란 택배가 있었다",
    "sentences": ["현관문", "앞에", "커다란", "택배가", "있었다"],
    "keyword": ["현관문", "앞", "커다란", "택배", "있었다"]
  },
  {
    "index": 67,
    "fullSentence": "작년에 아들이 미국으로 유학을 갔다",
    "sentences": ["작년에", "아들이", "미국으로", "유학을", "갔다"],
    "keyword": ["작년", "아들", "미국", "유학", "갔다"]
  },
  {
    "index": 68,
    "fullSentence": "여름에 부모님과 유럽 여행을 갔다",
    "sentences": ["여름에", "부모님과", "유럽", "여행을", "갔다"],
    "keyword": ["여름", "부모님", "유럽", "여행", "갔다"]
  },
  {
    "index": 69,
    "fullSentence": "하얀색 원피스를 입은 사람이 누나이다",
    "sentences": ["하얀색", "원피스를", "입은", "사람이", "누나이다"],
    "keyword": ["하얀색", "원피스", "입은", "사람", "누나이다"]
  },
  {
    "index": 70,
    "fullSentence": "언니는 나와 닮았지만 성격은 다르다",
    "sentences": ["언니는", "나와", "닮았지만", "성격은", "다르다"],
    "keyword": ["언니", "나", "닮았지만", "성격", "다르다"]
  },
  {
    "index": 71,
    "fullSentence": "어디선가 나를 부르는 소리가 들렸다",
    "sentences": ["어디선가", "나를", "부르는", "소리가", "들렸다"],
    "keyword": ["어디선가", "나", "부르는", "소리", "들렸다"]
  },
  {
    "index": 72,
    "fullSentence": "할머니는 매일 아침 체조를 하신다",
    "sentences": ["할머니는", "매일", "아침", "체조를", "하신다"],
    "keyword": ["할머니", "매일", "아침", "체조", "하신다"]
  },
  {
    "index": 73,
    "fullSentence": "남자 주인공이 키가 크고 멋있다",
    "sentences": ["남자", "주인공이", "키가", "크고", "멋있다"],
    "keyword": ["남자", "주인공", "키", "크고", "멋있다"]
  },
  {
    "index": 74,
    "fullSentence": "보일러가 고장나서 사무실 안이 추웠다",
    "sentences": ["보일러가", "고장나서", "사무실", "안이", "추웠다"],
    "keyword": ["보일러", "고장", "사무실", "안", "추웠다"]
  },
  {
    "index": 75,
    "fullSentence": "여름에 날씨가 더워서 선풍기를 샀다",
    "sentences": ["여름에", "날씨가", "더워서", "선풍기를", "샀다"],
    "keyword": ["여름", "날씨", "더워", "선풍기", "샀다"]
  },
  {
    "index": 76,
    "fullSentence": "책상 오른쪽에 이 층 침대가 있어요",
    "sentences": ["책상", "오른쪽에", "이 층", "침대가", "있어요"],
    "keyword": ["책상", "오른쪽", "이 층", "침대", "있어요"]
  },
  {
    "index": 77,
    "fullSentence": "교실에서 친구와 도시락을 같이 먹었다",
    "sentences": ["교실에서", "친구와", "도시락을", "같이", "먹었다"],
    "keyword": ["교실", "친구", "도시락", "같이", "먹었다"]
  },
  {
    "index": 78,
    "fullSentence": "재미있는 영화를 보고 실컷 웃었다",
    "sentences": ["재미있는", "영화를", "보고", "실컷", "웃었다"],
    "keyword": ["재미있는", "영화", "보고", "실컷", "웃었다"]
  },
  {
    "index": 79,
    "fullSentence": "가방을 보관해 주실 수 있나요",
    "sentences": ["가방을", "보관해", "주실", "수", "있나요"],
    "keyword": ["가방", "보관", "주실", "수", "있나요"]
  },
  {
    "index": 80,
    "fullSentence": "오랜만에 야외에 나왔더니 기분이 상쾌하다",
    "sentences": ["오랜만에", "야외에", "나왔더니", "기분이", "상쾌하다"],
    "keyword": ["오랜만", "야외", "나왔더니", "기분", "상쾌하다"]
  },
  {
    "index": 81,
    "fullSentence": "우리나라에는 아름다운 섬이 매우 많다",
    "sentences": ["우리나라에는", "아름다운", "섬이", "매우", "많다"],
    "keyword": ["우리나라", "아름다운", "섬", "매우", "많다"]
  },
  {
    "index": 82,
    "fullSentence": "침대와 옷장 사이에 화장대가 있다",
    "sentences": ["침대와", "옷장", "사이에", "화장대가", "있다"],
    "keyword": ["침대", "옷장", "사이", "화장대", "있다"]
  },
  {
    "index": 83,
    "fullSentence": "동물원에서는 겨울에 곰과 사자를 볼 수 있다",
    "sentences": ["동물원에서는", "겨울에", "곰과", "사자를", "볼 수 있다"],
    "keyword": ["동물원", "겨울", "곰", "사자", "볼 수 있다"]
  },
  {
    "index": 84,
    "fullSentence": "기차에서 내린 후에 숙소로 갔다",
    "sentences": ["기차에서", "내린", "후에", "숙소로", "갔다"],
    "keyword": ["기차", "내린", "후", "숙소", "갔다"]
  },
  {
    "index": 85,
    "fullSentence": "어려운 시험에 통과해서 기분이 좋다",
    "sentences": ["어려운", "시험에", "통과해서", "기분이", "좋다"],
    "keyword": ["어려운", "시험", "통과", "기분", "좋다"]
  },
  {
    "index": 86,
    "fullSentence": "휴지통은 부엌 식탁 밑에 있다",
    "sentences": ["휴지통은", "부엌", "식탁", "밑에", "있다"],
    "keyword": ["휴지통", "부엌", "식탁", "밑", "있다"]
  },
  {
    "index": 87,
    "fullSentence": "점심은 분식집에서 떡볶이와 김밥을 먹었다",
    "sentences": ["점심은", "분식집에서", "떡볶이와", "김밥을", "먹었다"],
    "keyword": ["점심", "분식집", "떡볶이", "김밥", "먹었다"]
  },
  {
    "index": 88,
    "fullSentence": "감기에 걸려서 저녁에 약을 먹었다",
    "sentences": ["감기에", "걸려서", "저녁에", "약을", "먹었다"],
    "keyword": ["감기", "걸려", "저녁", "약", "먹었다"]
  },
  {
    "index": 89,
    "fullSentence": "아침마다 방을 청소하고 빨래를 했습니다",
    "sentences": ["아침마다", "방을", "청소하고", "빨래를", "했습니다"],
    "keyword": ["아침", "방", "청소", "빨래", "했습니다"]
  },
  {
    "index": 90,
    "fullSentence": "아이들은 주말에 늦잠을 자고 싶어한다",
    "sentences": ["아이들은", "주말에", "늦잠을", "자고", "싶어한다"],
    "keyword": ["아이", "주말", "늦잠", "자고", "싶어한다"]
  },
  {
    "index": 91,
    "fullSentence": "저번주 금요일 저녁에 집으로 돌아왔다",
    "sentences": ["저번주", "금요일", "저녁에", "집으로", "돌아왔다"],
    "keyword": ["저번주", "금요일", "저녁", "집", "돌아왔다"]
  },
  {
    "index": 92,
    "fullSentence": "공부를 열심히 해서 반에서 일등을 했다",
    "sentences": ["공부를", "열심히 해서", "반에서", "일등을", "했다"],
    "keyword": ["공부", "열심히", "반", "일등", "했다"]
  },
  {
    "index": 93,
    "fullSentence": "숙소 근처에 넓은 공원이 있다",
    "sentences": ["숙소", "근처에", "넓은", "공원이", "있다"],
    "keyword": ["숙소", "근처", "넓은", "공원", "있다"]
  },
  {
    "index": 94,
    "fullSentence": "나는 내년 봄에 대학교에 입학한다",
    "sentences": ["나는", "내년", "봄에", "대학교에", "입학한다"],
    "keyword": ["나", "내년", "봄", "대학교", "입학한다"]
  },
  {
    "index": 95,
    "fullSentence": "식탁 위에 접시와 컵이 있다",
    "sentences": ["식탁", "위에", "접시와", "컵이", "있다"],
    "keyword": ["식탁", "위", "접시", "컵", "있다"]
  },
  {
    "index": 96,
    "fullSentence": "매일 학교에서 집까지 걸어서 간다",
    "sentences": ["매일", "학교에서", "집까지", "걸어서", "간다"],
    "keyword": ["매일", "학교", "집", "걸어", "간다"]
  },
  {
    "index": 97,
    "fullSentence": "오늘 본 영화의 주인공이 매력적이다",
    "sentences": ["오늘", "본", "영화의", "주인공이", "매력적이다"],
    "keyword": ["오늘", "본", "영화", "주인공", "매력적이다"]
  },
  {
    "index": 98,
    "fullSentence": "집의 분위기와 그림이 잘 어울린다",
    "sentences": ["집의", "분위기와", "그림이", "잘", "어울린다"],
    "keyword": ["집", "분위기", "그림", "잘", "어울린다"]
  },
  {
    "index": 99,
    "fullSentence": "웃는 표정을 보면 기분이 좋다",
    "sentences": ["웃는", "표정을", "보면", "기분이", "좋다"],
    "keyword": ["웃는", "표정", "보면", "기분", "좋다"]
  },
  {
    "index": 100,
    "fullSentence": "어젯밤에 태풍때문에 바람이 많이 불었다",
    "sentences": ["어젯밤에", "태풍때문에", "바람이", "많이", "불었다"],
    "keyword": ["어젯밤", "태풍", "바람", "많이", "불었다"]
  },
  {
    "index": 101,
    "fullSentence": "옷장 위에 귀여운 인형이 있습니다",
    "sentences": ["옷장", "위에", "귀여운", "인형이", "있습니다"],
    "keyword": ["옷장", "위", "귀여운", "인형", "있습니다"]
  },
  {
    "index": 102,
    "fullSentence": "집에 가는 길에 선생님을 만났다",
    "sentences": ["집에", "가는", "길에", "선생님을", "만났다"],
    "keyword": ["집", "가는", "길", "선생님", "만났다"]
  },
  {
    "index": 103,
    "fullSentence": "제일 가까운 은행은 어디에 있습니까",
    "sentences": ["제일", "가까운", "은행은", "어디에", "있습니까"],
    "keyword": ["제일", "가까운", "은행", "어디", "있습니까"]
  },
  {
    "index": 104,
    "fullSentence": "횡단보도를 건너기 전에 주위를 살피세요",
    "sentences": ["횡단보도를", "건너기", "전에", "주위를", "살피세요"],
    "keyword": ["횡단보도", "건너기", "전", "주위", "살피세요"]
  },
  {
    "index": 105,
    "fullSentence": "공부를 하다가 밖을 보니 어두워졌다",
    "sentences": ["공부를", "하다가", "밖을", "보니", "어두워졌다"],
    "keyword": ["공부", "하다가", "밖", "보니", "어두워졌다"]
  },
  {
    "index": 106,
    "fullSentence": "눈이 부셔서 앞을 볼 수가 없다",
    "sentences": ["눈이", "부셔서", "앞을", "볼 수가", "없다"],
    "keyword": ["눈", "부셔", "앞", "볼", "없다"]
  },
  {
    "index": 107,
    "fullSentence": "학생들에게 컴퓨터 사용하는 방법을 설명했다",
    "sentences": ["학생들에게", "컴퓨터", "사용하는", "방법을", "설명했다"],
    "keyword": ["학생들", "컴퓨터", "사용", "방법", "설명했다"]
  },
  {
    "index": 108,
    "fullSentence": "따뜻하고 푹신한 이불과 베개를 샀다",
    "sentences": ["따뜻하고", "푹신한", "이불과", "베개를", "샀다"],
    "keyword": ["따뜻", "푹신", "이불", "베개", "샀다"]
  },
  {
    "index": 109,
    "fullSentence": "열쇠가 없어서 문을 열 수 없었다",
    "sentences": ["열쇠가", "없어서", "문을", "열 수", "없었다"],
    "keyword": ["열쇠", "없어", "문", "열 수", "없었다"]
  },
  {
    "index": 110,
    "fullSentence": "축구를 하다가 발에 부상을 당했다",
    "sentences": ["축구를", "하다가", "발에", "부상을", "당했다"],
    "keyword": ["축구", "하다", "발", "부상", "당했다"]
  },
  {
    "index": 111,
    "fullSentence": "다른 사람들의 말에 귀를 기울인다",
    "sentences": ["다른", "사람들의", "말에", "귀를", "기울인다"],
    "keyword": ["다른", "사람들", "말", "귀", "기울인다"]
  },
  {
    "index": 112,
    "fullSentence": "친구를 기다리는동안 시계를 계속 봤다",
    "sentences": ["친구를", "기다리는동안", "시계를", "계속", "봤다"],
    "keyword": ["친구", "기다리는동안", "시계", "계속", "봤다"]
  },
  {
    "index": 113,
    "fullSentence": "졸업 후에 학교 선생님이 되고싶다",
    "sentences": ["졸업", "후에", "학교", "선생님이", "되고싶다"],
    "keyword": ["졸업", "후", "학교", "선생님", "되고싶다"]
  },
  {
    "index": 114,
    "fullSentence": "집 근처에 옷가게가 많이 있다",
    "sentences": ["집", "근처에", "옷가게가", "많이", "있다"],
    "keyword": ["집", "근처", "옷가게", "많이", "있다"]
  },
  {
    "index": 115,
    "fullSentence": "박물관에는 음식을 가지고 들어갈 수 없다",
    "sentences": ["박물관에는", "음식을", "가지고", "들어갈 수", "없다"],
    "keyword": ["박물관", "음식", "가지고", "들어갈", "없다"]
  },
  {
    "index": 116,
    "fullSentence": "맞은편 식당은 맛있는 부침개로 유명하다",
    "sentences": ["맞은편", "식당은", "맛있는", "부침개로", "유명하다"],
    "keyword": ["맞은편", "식당", "맛있는", "부침개", "유명하다"]
  },
  {
    "index": 117,
    "fullSentence": "미술관 안에서 사진을 찍으면 안된다",
    "sentences": ["미술관", "안에서", "사진을", "찍으면", "안된다"],
    "keyword": ["미술관", "안", "사진", "찍으면", "안된다"]
  },
  {
    "index": 118,
    "fullSentence": "태권도를 좋아하는 사람이면 누구나 환영합니다",
    "sentences": ["태권도를", "좋아하는", "사람이면", "누구나", "환영합니다"],
    "keyword": ["태권도", "좋아", "사람", "누구나", "환영합니다"]
  },
  {
    "index": 119,
    "fullSentence": "대부분의 아이들은 눈이 내리면 좋아한다",
    "sentences": ["대부분의", "아이들은", "눈이", "내리면", "좋아한다"],
    "keyword": ["대부분", "아이들", "눈", "내리면", "좋아한다"]
  },
  {
    "index": 120,
    "fullSentence": "손님이 조카에게 줄 만화책을 샀다",
    "sentences": ["손님이", "조카에게", "줄", "만화책을", "샀다"],
    "keyword": ["손님", "조카", "줄", "만화책", "샀다"]
  },
  {
    "index": 121,
    "fullSentence": "마을의 젊은 여자들이 그네를 탄다",
    "sentences": ["마을의", "젊은", "여자들이", "그네를", "탄다"],
    "keyword": ["마을", "젊은", "여자들", "그네", "탄다"]
  },
  {
    "index": 122,
    "fullSentence": "외출 후에는 손을 깨끗이 씻으세요",
    "sentences": ["외출", "후에는", "손을", "깨끗이", "씻으세요"],
    "keyword": ["외출", "후", "손", "깨끗이", "씻으세요"]
  },
  {
    "index": 123,
    "fullSentence": "오래전 봤던 드라마를 다시 보았다",
    "sentences": ["오래전", "봤던", "드라마를", "다시", "보았다"],
    "keyword": ["오래전", "봤던", "드라마", "다시", "보았다"]
  },
  {
    "index": 124,
    "fullSentence": "공원에서 자전거를 타고 집으로 갔다",
    "sentences": ["공원에서", "자전거를", "타고", "집으로", "갔다"],
    "keyword": ["공원", "자전거", "타고", "집", "갔다"]
  },
  {
    "index": 125,
    "fullSentence": "꽃과 나비가 있는 그림을 그렸다",
    "sentences": ["꽃과", "나비가", "있는", "그림을", "그렸다"],
    "keyword": ["꽃", "나비", "있는", "그림", "그렸다"]
  },
  {
    "index": 126,
    "fullSentence": "내일은 가게로 돈을 꼭 가져오세요",
    "sentences": ["내일은", "가게로", "돈을", "꼭", "가져오세요"],
    "keyword": ["내일", "가게", "돈", "꼭", "가져오세요"]
  },
  {
    "index": 127,
    "fullSentence": "과일 향이 나는 향수를 좋아한다",
    "sentences": ["과일", "향이", "나는", "향수를", "좋아한다"],
    "keyword": ["과일", "향", "나는", "향수", "좋아한다"]
  },
  {
    "index": 128,
    "fullSentence": "문이 열리는 소리에 깜짝 놀랐다",
    "sentences": ["문이", "열리는", "소리에", "깜짝", "놀랐다"],
    "keyword": ["문", "열리는", "소리", "깜짝", "놀랐다"]
  },
  {
    "index": 129,
    "fullSentence": "어머니가 만든 맛있는 음식이 그리워요",
    "sentences": ["어머니가", "만든", "맛있는", "음식이", "그리워요"],
    "keyword": ["어머니", "만든", "맛있는", "음식", "그리워요"]
  },
  {
    "index": 130,
    "fullSentence": "바다에서 배를 타고 낚시를 했다",
    "sentences": ["바다에서", "배를", "타고", "낚시를", "했다"],
    "keyword": ["바다", "배", "타고", "낚시", "했다"]
  },
  {
    "index": 131,
    "fullSentence": "누나는 이틀에 한 번 방을 청소한다",
    "sentences": ["누나는", "이틀에", "한 번", "방을", "청소한다"],
    "keyword": ["누나", "이틀", "한 번", "방", "청소한다"]
  },
  {
    "index": 132,
    "fullSentence": "새로 산 구두가 작아서 발이 아프다",
    "sentences": ["새로 산", "구두가", "작아서", "발이", "아프다"],
    "keyword": ["새로 산", "구두", "작아서", "발", "아프다"]
  },
  {
    "index": 133,
    "fullSentence": "물에 들어가기 전에 운동을 하세요",
    "sentences": ["물에", "들어가기", "전에", "운동을", "하세요"],
    "keyword": ["물", "들어가기", "전", "운동", "하세요"]
  },
  {
    "index": 134,
    "fullSentence": "여자가 남자에게 길을 가르쳐 주고있다",
    "sentences": ["여자가", "남자에게", "길을", "가르쳐", "주고있다"],
    "keyword": ["여자", "남자", "길", "가르쳐", "주고있다"]
  },
  {
    "index": 135,
    "fullSentence": "지금 티비에 나오는 운동화를 주문했다",
    "sentences": ["지금", "티비에", "나오는", "운동화를", "주문했다"],
    "keyword": ["지금", "티비", "나오는", "운동화", "주문했다"]
  },
  {
    "index": 136,
    "fullSentence": "마지막 버스를 놓쳐서 약속에 늦었다",
    "sentences": ["마지막", "버스를", "놓쳐서", "약속에", "늦었다"],
    "keyword": ["마지막", "버스", "놓쳐서", "약속", "늦었다"]
  },
  {
    "index": 137,
    "fullSentence": "경기장의 모든 자리는 가격이 동일하다",
    "sentences": ["경기장의", "모든", "자리는", "가격이", "동일하다"],
    "keyword": ["경기장", "모든", "자리", "가격", "동일하다"]
  },
  {
    "index": 138,
    "fullSentence": "오늘은 햇볕이 뜨거우니 모자를 준비하세요",
    "sentences": ["오늘은", "햇볕이", "뜨거우니", "모자를", "준비하세요"],
    "keyword": ["오늘", "햇볕", "뜨거우니", "모자", "준비하세요"]
  },
  {
    "index": 139,
    "fullSentence": "작년 생일에 향수를 선물로 받았다",
    "sentences": ["작년", "생일에", "향수를", "선물로", "받았다"],
    "keyword": ["작년", "생일", "향수", "선물", "받았다"]
  },
  {
    "index": 140,
    "fullSentence": "지금 도서관에 앉을 자리가 없다",
    "sentences": ["지금", "도서관에", "앉을", "자리가", "없다"],
    "keyword": ["지금", "도서관", "앉을", "자리", "없다"]
  },
  {
    "index": 141,
    "fullSentence": "배우가 노인 연기를 자연스럽게 잘했다",
    "sentences": ["배우가", "노인", "연기를", "자연스럽게", "잘했다"],
    "keyword": ["배우", "노인", "연기", "자연스럽게", "잘했다"]
  },
  {
    "index": 142,
    "fullSentence": "요즘 일이 많아서 정말 바쁘다",
    "sentences": ["요즘", "일이", "많아서", "정말", "바쁘다"],
    "keyword": ["요즘", "일", "많아서", "정말", "바쁘다"]
  },
  {
    "index": 143,
    "fullSentence": "요즘은 작고 가벼운 상품이 인기이다",
    "sentences": ["요즘은", "작고", "가벼운", "상품이", "인기이다"],
    "keyword": ["요즘", "작고", "가벼운", "상품", "인기이다"]
  },
  {
    "index": 144,
    "fullSentence": "라디오가 오래돼서 소리가 작게 나온다",
    "sentences": ["라디오가", "오래돼서", "소리가", "작게", "나온다"],
    "keyword": ["라디오", "오래", "소리", "작게", "나온다"]
  },
  {
    "index": 145,
    "fullSentence": "낙엽이 쌓이기 전에 치워야 한다",
    "sentences": ["낙엽이", "쌓이기", "전에", "치워야", "한다"],
    "keyword": ["낙엽", "쌓이기", "전", "치워야", "한다"]
  },
  {
    "index": 146,
    "fullSentence": "누나는 겨울에 스키를 자주 탑니다",
    "sentences": ["누나는", "겨울에", "스키를", "자주", "탑니다"],
    "keyword": ["누나", "겨울", "스키", "자주", "탑니다"]
  },
  {
    "index": 147,
    "fullSentence": "미리 가까운 식당을 예약해야 합니다",
    "sentences": ["미리", "가까운", "식당을", "예약해야", "합니다"],
    "keyword": ["미리", "가까운", "식당", "예약", "합니다"]
  },
  {
    "index": 148,
    "fullSentence": "친구들하고 새벽에 낚시를 가기로 했다",
    "sentences": ["친구들하고", "새벽에", "낚시를", "가기로", "했다"],
    "keyword": ["친구들", "새벽", "낚시", "가기로", "했다"]
  },
  {
    "index": 149,
    "fullSentence": "실례지만 여기 주유소가 어디에 있나요",
    "sentences": ["실례지만", "여기", "주유소가", "어디에", "있나요"],
    "keyword": ["실례지만", "여기", "주유소", "어디", "있나요"]
  },
  {
    "index": 150,
    "fullSentence": "목이 마른데 시원한 음료수를 주세요",
    "sentences": ["목이", "마른데", "시원한", "음료수를", "주세요"],
    "keyword": ["목", "마른데", "시원한", "음료수", "주세요"]
  },
  {
    "index": 151,
    "fullSentence": "오전 열 시에 친구를 만나기로 했다",
    "sentences": ["오전", "열 시에", "친구를", "만나기로", "했다"],
    "keyword": ["오전", "열 시", "친구", "만나기로", "했다"]
  },
  {
    "index": 152,
    "fullSentence": "청바지가 길어서 세탁소에 수선을 맡겼다",
    "sentences": ["청바지가", "길어서", "세탁소에", "수선을", "맡겼다"],
    "keyword": ["청바지", "길어서", "세탁소", "수선", "맡겼다"]
  },
  {
    "index": 153,
    "fullSentence": "방이 더워서 창문을 활짝 열었다",
    "sentences": ["방이", "더워서", "창문을", "활짝", "열었다"],
    "keyword": ["방", "더워서", "창문", "활짝", "열었다"]
  },
  {
    "index": 154,
    "fullSentence": "남편을 만나러 회사 앞으로 갔다",
    "sentences": ["남편을", "만나러", "회사", "앞으로", "갔다"],
    "keyword": ["남편", "만나러", "회사", "앞", "갔다"]
  },
  {
    "index": 155,
    "fullSentence": "청소를 안해서 옷장에서 냄새가 난다",
    "sentences": ["청소를", "안해서", "옷장에서", "냄새가", "난다"],
    "keyword": ["청소", "안해서", "옷장", "냄새", "난다"]
  },
  {
    "index": 156,
    "fullSentence": "학교 앞에 새로운 식당이 생겼다",
    "sentences": ["학교", "앞에", "새로운", "식당이", "생겼다"],
    "keyword": ["학교", "앞", "새로운", "식당", "생겼다"]
  },
  {
    "index": 157,
    "fullSentence": "사람들은 공연을 보고 박수를 쳤다",
    "sentences": ["사람들은", "공연을", "보고", "박수를", "쳤다"],
    "keyword": ["사람들", "공연", "보고", "박수", "쳤다"]
  },
  {
    "index": 158,
    "fullSentence": "배가 고파서 음식을 만들어 먹었다",
    "sentences": ["배가", "고파서", "음식을", "만들어", "먹었다"],
    "keyword": ["배", "고파서", "음식", "만들어", "먹었다"]
  },
  {
    "index": 159,
    "fullSentence": "선배에게 도움을 얻기위해 고민을 말했다",
    "sentences": ["선배에게", "도움을", "얻기위해", "고민을", "말했다"],
    "keyword": ["선배", "도움", "얻기위해", "고민", "말했다"]
  },
  {
    "index": 160,
    "fullSentence": "종이에 펜으로 이름과 전화번호를 썼다",
    "sentences": ["종이에", "펜으로", "이름과", "전화번호를", "썼다"],
    "keyword": ["종이", "펜", "이름", "전화번호", "썼다"]
  },
  {
    "index": 161,
    "fullSentence": "지금 밖에 눈과 비가 온다",
    "sentences": ["지금", "밖에", "눈과", "비가", "온다"],
    "keyword": ["지금", "밖", "눈", "비", "온다"]
  },
  {
    "index": 162,
    "fullSentence": "이번에 발표하신 작품 잘 읽었습니다",
    "sentences": ["이번에", "발표하신", "작품", "잘", "읽었습니다"],
    "keyword": ["이번", "발표", "작폼", "잘", "읽었습니다"]
  },
  {
    "index": 163,
    "fullSentence": "지도를 보면 금방 찾을 수 있다",
    "sentences": ["지도를", "보면", "금방", "찾을 수", "있다"],
    "keyword": ["지도", "보면", "금방", "찾을 수", "있다"]
  },
  {
    "index": 164,
    "fullSentence": "박물관에서 서울의 옛날 사진을 보았다",
    "sentences": ["박물관에서", "서울의", "옛날", "사진을", "보았다"],
    "keyword": ["박물관", "서울", "옛날", "사진", "보았다"]
  },
  {
    "index": 165,
    "fullSentence": "여름에는 가족들과 해외에 다녀올 계획이다",
    "sentences": ["여름에는", "가족들과", "해외에", "다녀올", "계획이다"],
    "keyword": ["여름", "가족", "해외", "다녀올", "계획이다"]
  },
  {
    "index": 166,
    "fullSentence": "큰 수박을 적당한 크기로 잘랐다",
    "sentences": ["큰", "수박을", "적당한", "크기로", "잘랐다"],
    "keyword": ["큰", "수박", "적당한", "크기", "잘랐다"]
  },
  {
    "index": 167,
    "fullSentence": "공연을 기다리는 사람이 너무 많다",
    "sentences": ["공연을", "기다리는", "사람이", "너무", "많다"],
    "keyword": ["공연", "기다리는", "사람", "너무", "많다"]
  },
  {
    "index": 168,
    "fullSentence": "얼마 전에 오래된 자동차를 샀다",
    "sentences": ["얼마", "전에", "오래된", "자동차를", "샀다"],
    "keyword": ["얼마", "전", "오래된", "자동차", "샀다"]
  },
  {
    "index": 169,
    "fullSentence": "내일부터 기온이 떨어져 추워질 예정이다",
    "sentences": ["내일부터", "기온이", "떨어져", "추워질", "예정이다"],
    "keyword": ["내일", "기온", "떨어져", "추워질", "예정이다"]
  },
  {
    "index": 170,
    "fullSentence": "시간이 없으니 다음에 다시 오세요",
    "sentences": ["시간이", "없으니", "다음에", "다시", "오세요"],
    "keyword": ["시간", "없으니", "다음", "다시", "오세요"]
  },
  {
    "index": 171,
    "fullSentence": "청소를 하려고 학교에 일찍 갔다",
    "sentences": ["청소를", "하려고", "학교에", "일찍", "갔다"],
    "keyword": ["청소", "하려고", "학교", "일찍", "갔다"]
  },
  {
    "index": 172,
    "fullSentence": "경기가 시작하면 바구니에 공을 넣으세요",
    "sentences": ["경기가", "시작하면", "바구니에", "공을", "넣으세요"],
    "keyword": ["경기", "시작", "바구니", "공", "넣으세요"]
  },
  {
    "index": 173,
    "fullSentence": "엄마는 평소에 커피와 녹차를 즐겨마신다",
    "sentences": ["엄마는", "평소에", "커피와", "녹차를", "즐겨마신다"],
    "keyword": ["엄마", "평소", "커피", "녹차", "즐겨마신다"]
  },
  {
    "index": 174,
    "fullSentence": "역에서 서울행 기차가 곧 출발한다",
    "sentences": ["역에서", "서울행", "기차가", "곧", "출발한다"],
    "keyword": ["역", "서울행", "기차", "곧", "출발한다"]
  },
  {
    "index": 175,
    "fullSentence": "여기서부터 정류장까지 거리가 너무 멀다",
    "sentences": ["여기서부터", "정류장까지", "거리가", "너무", "멀다"],
    "keyword": ["여기서부터", "정류장", "거리", "너무", "멀다"]
  },
  {
    "index": 176,
    "fullSentence": "설거지를 하시는 어머니의 손이 차갑다",
    "sentences": ["설거지를", "하시는", "어머니의", "손이", "차갑다"],
    "keyword": ["설거지", "하시는", "어머니", "손", "차갑다"]
  },
  {
    "index": 177,
    "fullSentence": "식탁에 있는 설탕 좀 주실래요",
    "sentences": ["식탁에", "있는", "설탕", "좀", "주실래요"],
    "keyword": ["식탁", "있는", "설탕", "좀", "주실래요"]
  },
  {
    "index": 178,
    "fullSentence": "한강에서 남자 친구와 자전거를 탔습니다",
    "sentences": ["한강에서", "남자", "친구와", "자전거를", "탔습니다"],
    "keyword": ["한강", "남자", "친구", "자전거", "탔습니다"]
  },
  {
    "index": 179,
    "fullSentence": "여동생은 강아지나 토끼같은 동물을 좋아한다",
    "sentences": ["여동생은", "강아지나", "토끼같은", "동물을", "좋아한다"],
    "keyword": ["여동생", "강아지", "토끼", "동물", "좋아한다"]
  },
  {
    "index": 180,
    "fullSentence": "청소 시간에 바닥과 창틀을 닦았다",
    "sentences": ["청소", "시간에", "바닥과", "창틀을", "닦았다"],
    "keyword": ["청소", "시간", "바닥", "창틀", "닦았다"]
  },
  {
    "index": 181,
    "fullSentence": "고개를 들고 팔을 앞으로 뻗어라",
    "sentences": ["고개를", "들고", "팔을", "앞으로", "뻗어라"],
    "keyword": ["고개", "들고", "팔", "앞", "뻗어라"]
  },
  {
    "index": 182,
    "fullSentence": "여름에는 수박과 참외가 시원하고 달다",
    "sentences": ["여름에는", "수박과", "참외가", "시원하고", "달다"],
    "keyword": ["여름", "수박", "참외", "시원", "달다"]
  },
  {
    "index": 183,
    "fullSentence": "오늘 수업이 끝나면 집에 전화하세요",
    "sentences": ["오늘", "수업이", "끝나면", "집에", "전화하세요"],
    "keyword": ["오늘", "수업", "끝나면", "집", "전화하세요"]
  },
  {
    "index": 184,
    "fullSentence": "의사의 괜찮다는 말을 듣고 안심했다",
    "sentences": ["의사의", "괜찮다는", "말을", "듣고", "안심했다"],
    "keyword": ["의사", "괜찮다", "말", "듣고", "안심했다"]
  },
  {
    "index": 185,
    "fullSentence": "김치는 냉장고같은 시원한 장소에 보관하세요",
    "sentences": ["김치는", "냉장고같은", "시원한", "장소에", "보관하세요"],
    "keyword": ["김치", "냉장고", "시원", "장소", "보관하세요"]
  },
  {
    "index": 186,
    "fullSentence": "방금 여자 친구에게 편지를 받았다",
    "sentences": ["방금", "여자", "친구에게", "편지를", "받았다"],
    "keyword": ["방금", "여자", "친구", "편지", "받았다"]
  },
  {
    "index": 187,
    "fullSentence": "여행을 가기 위해 돈을 열심히 벌었다",
    "sentences": ["여행을", "가기 위해", "돈을", "열심히", "벌었다"],
    "keyword": ["여행", "가기", "돈", "열심히", "벌었다"]
  },
  {
    "index": 188,
    "fullSentence": "은행에 돈을 맡기는 손님이 많다",
    "sentences": ["은행에", "돈을", "맡기는", "손님이", "많다"],
    "keyword": ["은행", "돈", "맡기는", "손님", "많다"]
  },
  {
    "index": 189,
    "fullSentence": "언니와 오빠는 오늘부터 회사에서 일한다",
    "sentences": ["언니와", "오빠는", "오늘부터", "회사에서", "일한다"],
    "keyword": ["언니", "오빠", "오늘", "회사", "일한다"]
  },
  {
    "index": 190,
    "fullSentence": "복도나 계단에서 뛰면 무척 위험하다",
    "sentences": ["복도나", "계단에서", "뛰면", "무척", "위험하다"],
    "keyword": ["복도", "계단", "뛰면", "무척", "위험하다"]
  },
  {
    "index": 191,
    "fullSentence": "오늘은 늦지않고 일찍 도착해서 다행이다",
    "sentences": ["오늘은", "늦지않고", "일찍", "도착해서", "다행이다"],
    "keyword": ["오늘", "늦지않고", "일찍", "도착", "다행이다"]
  },
  {
    "index": 192,
    "fullSentence": "이곳에서 컴퓨터와 필요한 책을 받으세요",
    "sentences": ["이곳에서", "컴퓨터와", "필요한", "책을", "받으세요"],
    "keyword": ["이곳", "컴퓨터", "필요한", "책", "받으세요"]
  },
  {
    "index": 193,
    "fullSentence": "아파트가 지어진지 오래돼서 지붕이 낡았다",
    "sentences": ["아파트가", "지어진지", "오래돼서", "지붕이", "낡았다"],
    "keyword": ["아파트", "지어진지", "오래", "지붕", "낡았다"]
  },
  {
    "index": 194,
    "fullSentence": "건물에 학생 휴게실은 어디에 있나요",
    "sentences": ["건물에", "학생", "휴게실은", "어디에", "있나요"],
    "keyword": ["건물", "학생", "휴게실", "어디", "있나요"]
  },
  {
    "index": 195,
    "fullSentence": "공부를 했더니 머리가 너무 아프다",
    "sentences": ["공부를", "했더니", "머리가", "너무", "아프다"],
    "keyword": ["공부", "했더니", "머리", "너무", "아프다"]
  },
  {
    "index": 196,
    "fullSentence": "오늘 병원에는 어디가 아파서 오셨나요",
    "sentences": ["오늘", "병원에는", "어디가", "아파서", "오셨나요"],
    "keyword": ["오늘", "병원", "어디", "아파서", "오셨나요"]
  },
  {
    "index": 197,
    "fullSentence": "음식을 먹기 전에 손을 씻었다",
    "sentences": ["음식을", "먹기", "전에", "손을", "씻었다"],
    "keyword": ["음식", "먹기", "전", "손", "씻었다"]
  },
  {
    "index": 198,
    "fullSentence": "한국과 미국의 음악을 자주 듣는다",
    "sentences": ["한국과", "미국의", "음악을", "자주", "듣는다"],
    "keyword": ["한국", "미국", "음악", "자주", "듣는다"]
  },
  {
    "index": 199,
    "fullSentence": "누가 창문을 활짝 열었는지 물었다",
    "sentences": ["누가", "창문을", "활짝", "열었는지", "물었다"],
    "keyword": ["누가", "창문", "활짝", "열었는지", "물었다"]
  },
  {
    "index": 200,
    "fullSentence": "다음주 화요일로 병원 예약을 변경했다",
    "sentences": ["다음주", "화요일로", "병원", "예약을", "변경했다"],
    "keyword": ["다음주", "화요일", "병원", "예약", "변경했다"]
  },
  {
    "index": 201,
    "fullSentence": "방을 깨끗한 걸레로 깨끗하게 청소했다",
    "sentences": ["방을", "깨끗한", "걸레로", "깨끗하게", "청소했다"],
    "keyword": ["방", "깨끗한", "걸레", "깨끗하게", "청소했다"]
  },
  {
    "index": 202,
    "fullSentence": "신발을 벗고 슬리퍼를 신고 들어가세요",
    "sentences": ["신발을", "벗고", "슬리퍼를", "신고", "들어가세요"],
    "keyword": ["신발", "벗고", "슬리퍼", "신고", "들어가세요"]
  },
  {
    "index": 203,
    "fullSentence": "아버지는 할아버지를 닮아 힘이 세다",
    "sentences": ["아버지는", "할아버지를", "닮아", "힘이", "세다"],
    "keyword": ["아버지", "할아버지", "닮아", "힘", "세다"]
  },
  {
    "index": 204,
    "fullSentence": "점심에 식당에서 국과 비빔밥을 먹었다",
    "sentences": ["점심에", "식당에서", "국과", "비빔밥을", "먹었다"],
    "keyword": ["점심", "식당", "국", "비빔밥", "먹었다"]
  },
  {
    "index": 205,
    "fullSentence": "아기는 장난감을 가지고 노는 것을 좋아한다",
    "sentences": ["아기는", "장난감을", "가지고", "노는 것을", "좋아한다"],
    "keyword": ["아기", "장난감", "가지고", "노는", "좋아한다"]
  },
  {
    "index": 206,
    "fullSentence": "부모님이 떠나자 아이가 울음을 터뜨렸다",
    "sentences": ["부모님이", "떠나자", "아이가", "울음을", "터뜨렸다"],
    "keyword": ["부모님", "떠나", "아이", "울음", "터뜨렸다"]
  },
  {
    "index": 207,
    "fullSentence": "집에 있는 오래된 책장이 멋스럽다",
    "sentences": ["집에", "있는", "오래된", "책장이", "멋스럽다"],
    "keyword": ["집", "있는", "오래된", "책장", "멋스럽다"]
  },
  {
    "index": 208,
    "fullSentence": "급식으로 나온 국이 너무 뜨겁다",
    "sentences": ["급식으로", "나온", "국이", "너무", "뜨겁다"],
    "keyword": ["급식", "나온", "국", "너무", "뜨겁다"]
  },
  {
    "index": 209,
    "fullSentence": "눈이 와서 길이 미끄러우니 조심해라",
    "sentences": ["눈이", "와서", "길이", "미끄러우니", "조심해라"],
    "keyword": ["눈", "와서", "길", "미끄러우니", "조심해라"]
  },
  {
    "index": 210,
    "fullSentence": "오늘은 눈이 내리니 장갑을 껴라",
    "sentences": ["오늘은", "눈이", "내리니", "장갑을", "껴라"],
    "keyword": ["오늘", "눈", "내리니", "장갑", "껴라"]
  },
  {
    "index": 211,
    "fullSentence": "식당에서 돈을 내려는데 지갑이 없었다",
    "sentences": ["식당에서", "돈을", "내려는데", "지갑이", "없었다"],
    "keyword": ["식당", "돈", "내려는데", "지갑", "없었다"]
  },
  {
    "index": 212,
    "fullSentence": "운동장에 나가기 전에 미리 알려주세요",
    "sentences": ["운동장에", "나가기", "전에", "미리", "알려주세요"],
    "keyword": ["운동장", "나가기", "전", "미리", "알려주세요"]
  },
  {
    "index": 213,
    "fullSentence": "꽃잎이 바람에 날려 경치가 아름답다",
    "sentences": ["꽃잎이", "바람에", "날려", "경치가", "아름답다"],
    "keyword": ["꽃입", "바람", "날려", "경치", "아름답다"]
  },
  {
    "index": 214,
    "fullSentence": "내일은 얇은 외투와 장화를 챙겨라",
    "sentences": ["내일은", "얇은", "외투와", "장화를", "챙겨라"],
    "keyword": ["내일", "얇은", "외투", "장화", "챙겨라"]
  },
  {
    "index": 215,
    "fullSentence": "공원을 걷다가 우연히 선생님을 보았다",
    "sentences": ["공원을", "걷다가", "우연히", "선생님을", "보았다"],
    "keyword": ["공원", "걷다", "우연히", "선생님", "보았다"]
  },
  {
    "index": 216,
    "fullSentence": "가로등이 골목에 있어서 길이 밝다",
    "sentences": ["가로등이", "골목에", "있어서", "길이", "밝다"],
    "keyword": ["가로등", "골목", "있어", "길", "밝다"]
  },
  {
    "index": 217,
    "fullSentence": "제주도는 멀어서 비행기를 타고 가야한다",
    "sentences": ["제주도는", "멀어서", "비행기를", "타고", "가야한다"],
    "keyword": ["제주도", "멀어", "비행기", "타고", "가야한다"]
  },
  {
    "index": 218,
    "fullSentence": "집에서 학교까지 걸어서 가기에는 멀다",
    "sentences": ["집에서", "학교까지", "걸어서", "가기에는", "멀다"],
    "keyword": ["집", "학교", "걸어", "가기", "멀다"]
  },
  {
    "index": 219,
    "fullSentence": "예쁜 꽃 한 다발을 샀다",
    "sentences": ["예쁜", "꽃", "한", "다발을", "샀다"],
    "keyword": ["예쁜", "꽃", "한", "다발", "샀다"]
  },
  {
    "index": 220,
    "fullSentence": "사무실 열쇠가 어디에 있는지 모른다",
    "sentences": ["사무실", "열쇠가", "어디에", "있는지", "모른다"],
    "keyword": ["사무실", "열쇠", "어디", "있는지", "모른다"]
  },
  {
    "index": 221,
    "fullSentence": "이번에 준비한 행사는 크고 근사하다",
    "sentences": ["이번에", "준비한", "행사는", "크고", "근사하다"],
    "keyword": ["이번", "준비", "행사", "크고", "근사하다"]
  },
  {
    "index": 222,
    "fullSentence": "의자 밑에서 잃어버린 지갑을 찾았다",
    "sentences": ["의자", "밑에서", "잃어버린", "지갑을", "찾았다"],
    "keyword": ["의자", "밑", "잃어버린", "지갑", "찾았다"]
  },
  {
    "index": 223,
    "fullSentence": "나비 그림은 예쁜 색종이로 만든 것이다",
    "sentences": ["나비", "그림은", "예쁜", "색종이로", "만든 것이다"],
    "keyword": ["나비", "그림", "예쁜", "색종이", "만든 것이다"]
  },
  {
    "index": 224,
    "fullSentence": "나의 희망은 유명한 가수가 되는 것이다",
    "sentences": ["나의", "희망은", "유명한", "가수가", "되는 것이다"],
    "keyword": ["나", "희망", "유명한", "가수", "되는 것이다"]
  },
  {
    "index": 225,
    "fullSentence": "오늘 저녁에는 음악을 즐겁게 들었다",
    "sentences": ["오늘", "저녁에는", "음악을", "즐겁게", "들었다"],
    "keyword": ["오늘", "저녁", "음악", "즐업게", "들었다"]
  },
  {
    "index": 226,
    "fullSentence": "시험을 위해서 공부를 늦게까지 했다",
    "sentences": ["시험을", "위해서", "공부를", "늦게까지", "했다"],
    "keyword": ["시험", "위해", "공부", "늦게", "했다"]
  },
  {
    "index": 227,
    "fullSentence": "선물은 준비한 사람의 정성이 중요하다",
    "sentences": ["선물은", "준비한", "사람의", "정성이", "중요하다"],
    "keyword": ["선물", "준비", "사람", "정성", "중요하다"]
  },
  {
    "index": 228,
    "fullSentence": "방이 추우니 외투를 위에 입어라",
    "sentences": ["방이", "추우니", "외투를", "위에", "입어라"],
    "keyword": ["방", "추우니", "외투", "위", "입어라"]
  },
  {
    "index": 229,
    "fullSentence": "마트에서 과자를 두 봉지씩 고른다",
    "sentences": ["마트에서", "과자를", "두", "봉지씩", "고른다"],
    "keyword": ["마트", "과자", "두", "봉지", "고른다"]
  },
  {
    "index": 230,
    "fullSentence": "이 쪽 계단을 이용해서 일 층으로 내려가세요",
    "sentences": ["이 쪽", "계단을", "이용해서", "일 층으로", "내려가세요"],
    "keyword": ["이 쪽", "계단", "이용", "일 층", "내려가세요"]
  },
  {
    "index": 231,
    "fullSentence": "아침에 삶은 국수는 언니가 먹었어요",
    "sentences": ["아침에", "삶은", "국수는", "언니가", "먹었어요"],
    "keyword": ["아침", "삶은", "국수", "언니", "먹었어요"]
  },
  {
    "index": 232,
    "fullSentence": "자료 신청 기록은 온라인으로 확인해요",
    "sentences": ["자료", "신청", "기록은", "온라인으로", "확인해요"],
    "keyword": ["자료", "신청", "기록", "온라인", "확인해요"]
  },
  {
    "index": 233,
    "fullSentence": "운동은 힘들지만 친구와 같이하니 신난다",
    "sentences": ["운동은", "힘들지만", "친구와", "같이하니", "신난다"],
    "keyword": ["운동", "힘들지만", "친구", "같이하니", "신난다"]
  },
  {
    "index": 234,
    "fullSentence": "비도 오는데 같이 우산을 쓸까요",
    "sentences": ["비도", "오는데", "같이", "우산을", "쓸까요"],
    "keyword": ["비", "오는데", "같이", "우산", "쓸까요"]
  },
  {
    "index": 235,
    "fullSentence": "노트에 적은 분홍 글씨가 예쁘다",
    "sentences": ["노트에", "적은", "분홍", "글씨가", "예쁘다"],
    "keyword": ["노트", "적은", "분홍", "글씨", "예쁘다"]
  },
  {
    "index": 236,
    "fullSentence": "길을 걷다가 고등학교 동창을 만났다",
    "sentences": ["길을", "걷다가", "고등학교", "동창을", "만났다"],
    "keyword": ["길", "걷다", "고등학교", "동창", "만났다"]
  },
  {
    "index": 237,
    "fullSentence": "오늘은 비가 내려 마당이 젖었다",
    "sentences": ["오늘은", "비가", "내려", "마당이", "젖었다"],
    "keyword": ["오늘", "비", "내려", "마당", "젖었다"]
  },
  {
    "index": 238,
    "fullSentence": "어제까지 서울에 있는 음식점에서 일했다",
    "sentences": ["어제까지", "서울에", "있는", "음식점에서", "일했다"],
    "keyword": ["어제", "서울", "있는", "음식점", "일했다"]
  },
  {
    "index": 239,
    "fullSentence": "누나는 텃밭에서 많은 채소를 키운다",
    "sentences": ["누나는", "텃밭에서", "많은", "채소를", "키운다"],
    "keyword": ["누나", "텃밭", "많은", "채소", "키운다"]
  },
  {
    "index": 240,
    "fullSentence": "시골은 도시보다 공기가 매우 깨끗하다",
    "sentences": ["시골은", "도시보다", "공기가", "매우", "깨끗하다"],
    "keyword": ["시골", "도시", "공기", "매우", "깨끗하다"]
  },
  {
    "index": 241,
    "fullSentence": "배가 아파서 오후에 병원을 갔다",
    "sentences": ["배가", "아파서", "오후에", "병원을", "갔다"],
    "keyword": ["배", "아파", "오후", "병원", "갔다"]
  },
  {
    "index": 242,
    "fullSentence": "여름에 해변에서 사진을 많이 찍었다",
    "sentences": ["여름에", "해변에서", "사진을", "많이", "찍었다"],
    "keyword": ["여름", "해변", "사진", "많이", "찍었다"]
  },
  {
    "index": 243,
    "fullSentence": "길이 밀려서 등교 시간에 늦었다",
    "sentences": ["길이", "밀려서", "등교", "시간에", "늦었다"],
    "keyword": ["길", "밀려서", "등교", "시간", "늦었다"]
  },
  {
    "index": 244,
    "fullSentence": "산과 바다 중 어디로 갈지 고민이다",
    "sentences": ["산과", "바다 중", "어디로", "갈지", "고민이다"],
    "keyword": ["산", "바다 중", "어디", "갈지", "고민이다"]
  },
  {
    "index": 245,
    "fullSentence": "과자를 급하게 삼키면 목이 막힐 수 있다",
    "sentences": ["과자를", "급하게", "삼키면", "목이 막힐", "수 있다"],
    "keyword": ["과자", "급하게", "삼키면", "목", "막힐 수 있다"]
  },
  {
    "index": 246,
    "fullSentence": "근처에 공장이 있어서 많이 시끄럽다",
    "sentences": ["근처에", "공장이", "있어서", "많이", "시끄럽다"],
    "keyword": ["근처", "공장", "있어서", "많이", "시끄럽다"]
  },
  {
    "index": 247,
    "fullSentence": "마음이 약해서 고민이 자꾸 깊어진다",
    "sentences": ["마음이", "약해서", "고민이", "자꾸", "깊어진다"],
    "keyword": ["마음이", "약해서", "고민", "자꾸", "깊어진다"]
  },
  {
    "index": 248,
    "fullSentence": "입고 싶은 옷을 먼저 찾았다",
    "sentences": ["입고", "싶은", "옷을", "먼저", "찾았다"],
    "keyword": ["입고", "싶은", "옷", "먼저", "찾았다"]
  },
  {
    "index": 249,
    "fullSentence": "아이는 졸려서 스르르 눈을 감았다",
    "sentences": ["아이는", "졸려서", "스르르", "눈을", "감았다"],
    "keyword": ["아이", "졸려서", "스르르", "눈", "감았다"]
  },
  {
    "index": 250,
    "fullSentence": "고양이가 반짝이는 눈으로 아이를 바라보았다",
    "sentences": ["고양이가", "반짝이는", "눈으로", "아이를", "바라보았다"],
    "keyword": ["고양이", "반짝", "눈", "아이", "바라보았다"]
  },
  {
    "index": 251,
    "fullSentence": "버스를 타고 동생의 생일파티에 갔다.",
    "sentences": ["버스를", "타고", "동생의", "생일파티에", "갔다."],
    "keyword": ["버스", "타고", "동생", "생일", "갔다"]
  },
  {
    "index": 252,
    "fullSentence": "오늘 본 책이 꽤 흥미롭다",
    "sentences": ["오늘", "본", "책이", "꽤", "흥미롭다"],
    "keyword": ["오늘", "본", "책", "꽤", "흥미롭다"]
  },
  {
    "index": 253,
    "fullSentence": "아침에 비가 와서 도로가 미끄럽다",
    "sentences": ["아침에", "비가", "와서", "도로가", "미끄럽다"],
    "keyword": ["아침", "비", "와서", "도로", "미끄럽다"]
  },
  {
    "index": 254,
    "fullSentence": "공원에 멋진 놀이 기구가 있다",
    "sentences": ["공원에", "멋진", "놀이", "기구가", "있다"],
    "keyword": ["공원", "멋진", "놀이", "기구", "있다"]
  },
  {
    "index": 255,
    "fullSentence": "길을 걸으며 계속 이야기를 했다",
    "sentences": ["길을", "걸으며", "계속", "이야기를", "했다"],
    "keyword": ["길", "걸으며", "계속", "이야기", "했다"]
  },
  {
    "index": 256,
    "fullSentence": "높은 파도 속에서 수영을 했다",
    "sentences": ["높은", "파도", "속에서", "수영을", "했다"],
    "keyword": ["높은", "파도", "속", "수영", "했다"]
  },
  {
    "index": 257,
    "fullSentence": "날이 더우니 옷을 얇게 입어라",
    "sentences": ["날이", "더우니", "옷을", "얇게", "입어라"],
    "keyword": ["날", "더우니", "옷", "얇게", "입어라"]
  },
  {
    "index": 258,
    "fullSentence": "아침에 배를 타고 항구에 도착했다",
    "sentences": ["아침에", "배를", "타고", "항구에", "도착했다"],
    "keyword": ["아침", "배", "타고", "항구", "도착했다"]
  },
  {
    "index": 259,
    "fullSentence": "배가 고파서 식당에서 밥을 먹었다",
    "sentences": ["배가", "고파서", "식당에서", "밥을", "먹었다"],
    "keyword": ["배", "고파서", "식당", "밥", "먹었다"]
  },
  {
    "index": 260,
    "fullSentence": "시험이 끝나고 저녁을 먹으러 갔다",
    "sentences": ["시험이", "끝나고", "저녁을", "먹으러", "갔다"],
    "keyword": ["시험", "끝나고", "저녁", "먹으러", "갔다"]
  },
  {
    "index": 261,
    "fullSentence": "주말에 집으로 친구가 오기로 하였다",
    "sentences": ["주말에", "집으로", "친구가", "오기로", "하였다"],
    "keyword": ["주말", "집", "친구", "오기로", "하였다"]
  },
  {
    "index": 262,
    "fullSentence": "아빠는 날씨가 더워서 에어컨을 틀었다",
    "sentences": ["아빠는", "날씨가", "더워서", "에어컨을", "틀었다"],
    "keyword": ["아빠", "날씨", "더워", "에어컨", "틀었다"]
  },
  {
    "index": 263,
    "fullSentence": "엄마가 동생에게 자장가를 불러주고 있다",
    "sentences": ["엄마가", "동생에게", "자장가를", "불러주고", "있다"],
    "keyword": ["엄마", "동생", "자장가", "불러주고", "있다"]
  },
  {
    "index": 264,
    "fullSentence": "부산행 버스가 매일 새벽에 출발해요",
    "sentences": ["부산행", "버스가", "매일", "새벽에", "출발해요"],
    "keyword": ["부산행", "버스", "매일", "새벽", "출발해요"]
  },
  {
    "index": 265,
    "fullSentence": "동생은 운동보다 음악을 더 좋아해요",
    "sentences": ["동생은", "운동보다", "음악을", "더", "좋아해요"],
    "keyword": ["동생", "운동", "음악", "더", "좋아해요"]
  },
  {
    "index": 266,
    "fullSentence": "아침부터 비가 주륵주륵 내리기 시작했다",
    "sentences": ["아침부터", "비가", "주륵주륵", "내리기", "시작했다"],
    "keyword": ["아침", "비", "주륵주륵", "내리기", "시작했다"]
  },
  {
    "index": 267,
    "fullSentence": "여름 휴가로 어디를 갈지 고민이다",
    "sentences": ["여름", "휴가로", "어디를", "갈지", "고민이다"],
    "keyword": ["여름", "휴가", "어디", "갈지", "고민이다"]
  },
  {
    "index": 268,
    "fullSentence": "버스에서 내린 뒤에 주위를 둘러봤다",
    "sentences": ["버스에서", "내린", "뒤에", "주위를", "둘러봤다"],
    "keyword": ["버스", "내린", "뒤", "주위", "둘러봤다"]
  },
  {
    "index": 269,
    "fullSentence": "가끔 버스를 타고 퇴근을 합니다",
    "sentences": ["가끔", "버스를", "타고", "퇴근을", "합니다"],
    "keyword": ["가끔", "버스", "타고", "퇴근", "합니다"]
  },
  {
    "index": 270,
    "fullSentence": "힘든 일을 오래해서 몸이 피곤하다",
    "sentences": ["힘든", "일을", "오래해서", "몸이", "피곤하다"],
    "keyword": ["힘든", "일", "오래", "몸", "피곤하다"]
  },
  {
    "index": 271,
    "fullSentence": "꽃을 넣기에는 병의 크기가 작다",
    "sentences": ["꽃을", "넣기에는", "병의", "크기가", "작다"],
    "keyword": ["꽃", "넣기", "병", "크기", "작다"]
  },
  {
    "index": 272,
    "fullSentence": "형은 자전거를 타고 학교에 간다",
    "sentences": ["형은", "자전거를", "타고", "학교에", "간다"],
    "keyword": ["형", "자전거", "타고", "학교", "간다"]
  },
  {
    "index": 273,
    "fullSentence": "바람이 불어 우산이 날아갈 것 같다",
    "sentences": ["바람이", "불어", "우산이", "날아갈 것", "같다"],
    "keyword": ["바람", "불어", "우산", "날아갈", "같다"]
  },
  {
    "index": 274,
    "fullSentence": "친구가 군대에 가서 편지를 보냈다",
    "sentences": ["친구가", "군대에", "가서", "편지를", "보냈다"],
    "keyword": ["친구", "군대", "가서", "편지", "보냈다"]
  },
  {
    "index": 275,
    "fullSentence": "비가 내려서 창문을 닫고 나왔다",
    "sentences": ["비가", "내려서", "창문을", "닫고", "나왔다"],
    "keyword": ["비", "내려", "창문", "닫고", "나왔다"]
  },
  {
    "index": 276,
    "fullSentence": "나무의 열매가 완전히 익어서 떨어졌다",
    "sentences": ["나무의", "열매가", "완전히", "익어서", "떨어졌다"],
    "keyword": ["나무", "열매", "완전히", "익어", "떨어졌다"]
  },
  {
    "index": 277,
    "fullSentence": "남자는 운동을 하기위해 공원으로 갔다",
    "sentences": ["남자는", "운동을", "하기위해", "공원으로", "갔다"],
    "keyword": ["남자", "운동", "하기위해", "공원", "갔다"]
  },
  {
    "index": 278,
    "fullSentence": "주말엔 수업을 들으러 학원에 간다",
    "sentences": ["주말엔", "수업을", "들으러", "학원에", "간다"],
    "keyword": ["주말", "수업", "들으러", "학원", "간다"]
  },
  {
    "index": 279,
    "fullSentence": "옷장에 오래된 바지가 몇 개 있다",
    "sentences": ["옷장에", "오래된", "바지가", "몇 개", "있다"],
    "keyword": ["옷장", "우래된", "바지", "몇 개", "있다"]
  },
  {
    "index": 280,
    "fullSentence": "날이 더워 시원한 물이 마시고싶다",
    "sentences": ["날이", "더워", "시원한", "물이", "마시고싶다"],
    "keyword": ["날", "더워", "시원한", "물", "마시고싶다"]
  },
  {
    "index": 281,
    "fullSentence": "가게에 있는 옷을 편하게 입어보세요",
    "sentences": ["가게에", "있는", "옷을", "편하게", "입어보세요"],
    "keyword": ["가게", "있는", "옷", "편하게", "입어보세요"]
  },
  {
    "index": 282,
    "fullSentence": "눈이 내린 뒤에는 조심히 걸어가세요",
    "sentences": ["눈이", "내린", "뒤에는", "조심히", "걸어가세요"],
    "keyword": ["눈", "내린", "뒤", "조심히", "걸어가세요"]
  },
  {
    "index": 283,
    "fullSentence": "어제는 더워서 얇은 옷을 입었다",
    "sentences": ["어제는", "더워서", "얇은", "옷을", "입었다"],
    "keyword": ["어제", "더워", "얇은", "옷", "입었다"]
  },
  {
    "index": 284,
    "fullSentence": "몸이 아파서 급하게 병원에 갔다",
    "sentences": ["몸이", "아파서", "급하게", "병원에", "갔다"],
    "keyword": ["몸", "아파", "급하게", "병원", "갔다"]
  },
  {
    "index": 285,
    "fullSentence": "유명한 음식점에는 항상 손님이 많다",
    "sentences": ["유명한", "음식점에는", "항상", "손님이", "많다"],
    "keyword": ["유명한", "음식점", "항상", "손님", "많다"]
  },
  {
    "index": 286,
    "fullSentence": "문을 여니 차가운 바람이 느껴진다",
    "sentences": ["문을", "여니", "차가운", "바람이", "느껴진다"],
    "keyword": ["문", "여니", "차가운", "바람", "느껴진다"]
  },
  {
    "index": 287,
    "fullSentence": "공기가 맑을 때는 소풍을 간다",
    "sentences": ["공기가", "맑을", "때는", "소풍을", "간다"],
    "keyword": ["공기", "맑을", "때", "소풍", "간다"]
  },
  {
    "index": 288,
    "fullSentence": "탁자 옆에 큰 의자가 있다",
    "sentences": ["탁자", "옆에", "큰", "의자가", "있다"],
    "keyword": ["탁자", "옆", "큰", "의자", "있다"]
  },
  {
    "index": 289,
    "fullSentence": "배가 떠나기 전에 구명조끼를 입었다",
    "sentences": ["배가", "떠나기", "전에", "구명조끼를", "입었다"],
    "keyword": ["배", "떠나기", "전", "구명조끼", "입었다"]
  },
  {
    "index": 290,
    "fullSentence": "눈이 내리면 아이들은 눈사람을 만든다",
    "sentences": ["눈이", "내리면", "아이들은", "눈사람을", "만든다"],
    "keyword": ["눈", "내리면", "아이들", "눈사람", "만든다"]
  },
  {
    "index": 291,
    "fullSentence": "식당에서 밥을 먹으며 티비를 보았다",
    "sentences": ["식당에서", "밥을", "먹으며", "티비를", "보았다"],
    "keyword": ["식당", "밥", "먹으며", "티비", "보았다"]
  },
  {
    "index": 292,
    "fullSentence": "오늘 잡은 물고기를 어항에 넣었다",
    "sentences": ["오늘", "잡은", "물고기를", "어항에", "넣었다"],
    "keyword": ["오늘", "잡은", "물고기", "어항", "넣었다"]
  },
  {
    "index": 293,
    "fullSentence": "친구와 함께 약속 장소에서 기다렸다",
    "sentences": ["친구와", "함께", "약속", "장소에서", "기다렸다"],
    "keyword": ["친구", "함께", "약속", "장소", "기다렸다"]
  },
  {
    "index": 294,
    "fullSentence": "차를 세우고 바다 풍경을 보았다",
    "sentences": ["차를", "세우고", "바다", "풍경을", "보았다"],
    "keyword": ["차", "세우고", "바다", "풍경", "보았다"]
  },
  {
    "index": 295,
    "fullSentence": "병에 걸려서 치료를 오래 받았다",
    "sentences": ["병에", "걸려서", "치료를", "오래", "받았다"],
    "keyword": ["병", "걸려", "치료", "오래", "받았다"]
  },
  {
    "index": 296,
    "fullSentence": "초코 우유와 좋아하는 빵을 사세요",
    "sentences": ["초코", "우유와", "좋아하는", "빵을", "사세요"],
    "keyword": ["초코", "우유", "좋아하는", "빵", "사세요"]
  },
  {
    "index": 297,
    "fullSentence": "아이가 사탕을 양손 가득 가져왔다",
    "sentences": ["아이가", "사탕을", "양손", "가득", "가져왔다"],
    "keyword": ["아이", "사탕", "양손", "가득", "가져왔다"]
  },
  {
    "index": 298,
    "fullSentence": "여행을 떠나기 전에 가방을 쌌다",
    "sentences": ["여행을", "떠나기", "전에", "가방을", "쌌다"],
    "keyword": ["여행", "떠나기", "전", "가방", "쌌다"]
  },
  {
    "index": 299,
    "fullSentence": "길이 어두워서 밖에 나가지 못했다",
    "sentences": ["길이", "어두워서", "밖에", "나가지", "못했다"],
    "keyword": ["길", "어두워", "밖", "나가지", "못했다"]
  },
  {
    "index": 300,
    "fullSentence": "오랜만에 친척들을 보니 기분이 좋다",
    "sentences": ["오랜만에", "친척들을", "보니", "기분이", "좋다"],
    "keyword": ["오랜만", "친척들", "보니", "기분", "좋다"]
  },
  {
    "index": 301,
    "fullSentence": "조용한 서점에서 오랜시간 책을 읽었다",
    "sentences": ["조용한", "서점에서", "오랜시간", "책을", "읽었다"],
    "keyword": ["조옹한", "서점", "오랜", "책", "읽었다"]
  },
  {
    "index": 302,
    "fullSentence": "버스 정류장에 많은 사람들이 서있다",
    "sentences": ["버스", "정류장에", "많은", "사람들이", "서있다"],
    "keyword": ["버스", "정류장", "많은", "사람들", "서있다"]
  },
  {
    "index": 303,
    "fullSentence": "뉴스에 새로운 정보가 매일 공개된다",
    "sentences": ["뉴스에", "새로운", "정보가", "매일", "공개된다"],
    "keyword": ["뉴스", "새로운", "정보", "매일", "공개된다"]
  },
  {
    "index": 304,
    "fullSentence": "공원에서 가족들이 함께 사진을 찍는다",
    "sentences": ["공원에서", "가족들이", "함께", "사진을", "찍는다"],
    "keyword": ["공원", "가족", "함께", "사진", "찍는다"]
  },
  {
    "index": 305,
    "fullSentence": "학교 앞에서는 속도를 더 낮추세요",
    "sentences": ["학교", "앞에서는", "속도를", "더", "낮추세요"],
    "keyword": ["학교", "앞", "속도", "더", "낮추세요"]
  },
  {
    "index": 306,
    "fullSentence": "우체국에 가서 박스와 봉투를 찾았다",
    "sentences": ["우체국에", "가서", "박스와", "봉투를", "찾았다"],
    "keyword": ["우체국", "가서", "박스", "봉투", "찾았다"]
  },
  {
    "index": 307,
    "fullSentence": "섬으로 가는 배는 어디에서 탑니까",
    "sentences": ["섬으로", "가는", "배는", "어디에서", "탑니까"],
    "keyword": ["섬", "가는", "배", "어디", "탑니까"]
  },
  {
    "index": 308,
    "fullSentence": "좋은 시설을 이용하려면 돈을 내야한다",
    "sentences": ["좋은", "시설을", "이용하려면", "돈을", "내야한다"],
    "keyword": ["좋은", "시설", "이용", "돈", "내야한다"]
  },
  {
    "index": 309,
    "fullSentence": "기쁜 소식이 있으면 이웃과 나누세요",
    "sentences": ["기쁜", "소식이", "있으면", "이웃과", "나누세요"],
    "keyword": ["기쁜", "소식", "있으면", "이웃", "나누세요"]
  },
  {
    "index": 310,
    "fullSentence": "커피에 설탕을 넣고 여러 번 저었다",
    "sentences": ["커피에", "설탕을", "넣고", "여러 번", "저었다"],
    "keyword": ["커피", "설탕", "넣고", "여러 번", "저었다"]
  },
  {
    "index": 311,
    "fullSentence": "학교에서 상으로 받은 선물이 좋다",
    "sentences": ["학교에서", "상으로", "받은", "선물이", "좋다"],
    "keyword": ["학교", "상", "받은", "선물", "좋다"]
  },
  {
    "index": 312,
    "fullSentence": "보성은 한옥과 녹차로 유명한 장소이다",
    "sentences": ["보성은", "한옥과", "녹차로", "유명한", "장소이다"],
    "keyword": ["보성", "한옥", "녹차", "유명한", "장소"]
  },
  {
    "index": 313,
    "fullSentence": "여기가 음악 공연장으로 가는 길이다",
    "sentences": ["여기가", "음악", "공연장으로", "가는", "길이다"],
    "keyword": ["여기", "음악", "공연장", "가는", "길이다"]
  },
  {
    "index": 314,
    "fullSentence": "매일 밤 하늘에 별빛이 보인다",
    "sentences": ["매일", "밤", "하늘에", "별빛이", "보인다"],
    "keyword": ["매일", "밤", "하늘", "별빛", "보인다"]
  },
  {
    "index": 315,
    "fullSentence": "바람이 부는 언덕은 경사가 높다",
    "sentences": ["바람이", "부는", "언덕은", "경사가", "높다"],
    "keyword": ["바람", "부는", "언덕", "경사", "높다"]
  },
  {
    "index": 316,
    "fullSentence": "귤을 사러가는데 가게가 어디에 있나요",
    "sentences": ["귤을", "사러가는데", "가게가", "어디에", "있나요"],
    "keyword": ["귤", "사러가는데", "가게", "어디", "있나요"]
  },
  {
    "index": 317,
    "fullSentence": "축제를 할 때 광장이 많이 복잡하다",
    "sentences": ["축제를", "할 때", "광장이", "많이", "복잡하다"],
    "keyword": ["축제", "할 때", "광장", "많이", "복잡하다"]
  },
  {
    "index": 318,
    "fullSentence": "공원에 가서 코스모스와 국화를 보았다",
    "sentences": ["공원에", "가서", "코스모스와", "국화를", "보았다"],
    "keyword": ["공원", "가서", "코스모스", "국화", "보았다"]
  },
  {
    "index": 319,
    "fullSentence": "버스가 곧 오니 빨리 밖으로 나가자",
    "sentences": ["버스가", "곧 오니", "빨리", "밖으로", "나가자"],
    "keyword": ["버스", "곧 오니", "빨리", "밖", "나가자"]
  },
  {
    "index": 320,
    "fullSentence": "그릇을 사용하기 전에 설거지를 하세요",
    "sentences": ["그릇을", "사용하기", "전에", "설거지를", "하세요"],
    "keyword": ["그릇", "사용", "전", "설거지", "하세요"]
  },
  {
    "index": 321,
    "fullSentence": "연극을 보고 큰 감동을 받았다",
    "sentences": ["연극을", "보고", "큰", "감동을", "받았다"],
    "keyword": ["연극", "보고", "큰", "감동", "받았다"]
  },
  {
    "index": 322,
    "fullSentence": "병원에서 치료를 받고 약을 먹었습니다",
    "sentences": ["병원에서", "치료를", "받고", "약을", "먹었습니다"],
    "keyword": ["병원", "치료", "받고", "약", "먹었습니다"]
  },
  {
    "index": 323,
    "fullSentence": "화분에 흙을 넣고 식물을 키웠다",
    "sentences": ["화분에", "흙을", "넣고", "식물을", "키웠다"],
    "keyword": ["화분", "흙", "넣고", "식물", "키웠다"]
  },
  {
    "index": 324,
    "fullSentence": "어제는 피곤해서 일찍 잠에 들었다",
    "sentences": ["어제는", "피곤해서", "일찍", "잠에", "들었다"],
    "keyword": ["어제", "피곤", "일찍", "잠", "들었다"]
  },
  {
    "index": 325,
    "fullSentence": "물감과 색연필 중에 어떤 게 좋을까요",
    "sentences": ["물감과", "색연필", "중에", "어떤 게", "좋을까요"],
    "keyword": ["물감", "색연필", "중", "어떤 게", "좋을까요"]
  },
  {
    "index": 326,
    "fullSentence": "가방에 연필이 두 자루 있었다",
    "sentences": ["가방에", "연필이", "두", "자루", "있었다"],
    "keyword": ["가방", "연필", "두", "자루", "있었다"]
  },
  {
    "index": 327,
    "fullSentence": "대전으로 가는 기차가 방금 출발했다",
    "sentences": ["대전으로", "가는", "기차가", "방금", "출발했다"],
    "keyword": ["대전", "가는", "기차", "방금", "출발했다"]
  },
  {
    "index": 328,
    "fullSentence": "시장이 열려서 배추와 오이를 샀다",
    "sentences": ["시장이", "열려서", "배추와", "오이를", "샀다"],
    "keyword": ["시장", "열려", "배추", "오이", "샀다"]
  },
  {
    "index": 329,
    "fullSentence": "영화에서 가장 감동적인 장면은 무엇입니까",
    "sentences": ["영화에서", "가장", "감동적인", "장면은", "무엇입니까"],
    "keyword": ["영화", "가장", "감동", "장면", "무엇입니까"]
  },
  {
    "index": 330,
    "fullSentence": "추운 날 가족들과 함께 스프를 먹었다",
    "sentences": ["추운 날", "가족들과", "함께", "스프를", "먹었다"],
    "keyword": ["추운 날", "가족들", "함께", "스프", "먹었다"]
  },
  {
    "index": 331,
    "fullSentence": "밥을 먹고 몸의 기운이 살아났다",
    "sentences": ["밥을", "먹고", "몸의", "기운이", "살아났다"],
    "keyword": ["밥", "먹고", "몸", "기운", "살아났다"]
  },
  {
    "index": 332,
    "fullSentence": "서류를 제출하기 전에 내용을 정리했다",
    "sentences": ["서류를", "제출하기", "전에", "내용을", "정리했다"],
    "keyword": ["서류", "제출", "전", "내용", "정리했다"]
  },
  {
    "index": 333,
    "fullSentence": "누나는 울음을 참느라 정신이 없다",
    "sentences": ["누나는", "울음을", "참느라", "정신이", "없다"],
    "keyword": ["누나", "울음", "참느라", "정신", "없다"]
  },
  {
    "index": 334,
    "fullSentence": "졸업 후에 사람들과 모임을 가졌다",
    "sentences": ["졸업", "후에", "사람들과", "모임을", "가졌다"],
    "keyword": ["졸업", "후", "사람들", "모임", "가졌다"]
  },
  {
    "index": 335,
    "fullSentence": "공원이 새롭게 조성되어 화단이 깨끗하다",
    "sentences": ["공원이", "새롭게", "조성되어", "화단이", "깨끗하다"],
    "keyword": ["공원", "새롭게", "조성", "화단", "깨끗하다"]
  },
  {
    "index": 336,
    "fullSentence": "남은 재료로 음식을 만들어 주세요",
    "sentences": ["남은", "재료로", "음식을", "만들어", "주세요"],
    "keyword": ["남은", "재료", "음식", "만들어", "주세요"]
  },
  {
    "index": 337,
    "fullSentence": "부탁한 짐을 우체국 택배로 보냈다",
    "sentences": ["부탁한", "짐을", "우체국", "택배로", "보냈다"],
    "keyword": ["부탁한", "짐", "우체국", "택배", "보냈다"]
  },
  {
    "index": 338,
    "fullSentence": "공장에서 컵과 단단한 그릇을 만든다",
    "sentences": ["공장에서", "컵과", "단단한", "그릇을", "만든다"],
    "keyword": ["공장", "컵", "단단한", "그릇", "만든다"]
  },
  {
    "index": 339,
    "fullSentence": "신발이 젖어서 걷는 것이 불편하다",
    "sentences": ["신발이", "젖어서", "걷는", "것이", "불편하다"],
    "keyword": ["신발", "젖어", "걷는", "것", "불편하다"]
  },
  {
    "index": 340,
    "fullSentence": "학교에서 경제를 이해하는 지식을 배웠다",
    "sentences": ["학교에서", "경제를", "이해하는", "지식을", "배웠다"],
    "keyword": ["학교", "경제", "이해하는", "지식", "배웠다"]
  },
  {
    "index": 341,
    "fullSentence": "아파트에 많은 차량이 주차 되어있다",
    "sentences": ["아파트에", "많은", "차량이", "주차", "되어있다"],
    "keyword": ["아파트", "많은", "차량", "주차", "되어있다"]
  },
  {
    "index": 342,
    "fullSentence": "미용실에 손님이 많아서 오래 걸렸다",
    "sentences": ["미용실에", "손님이", "많아서", "오래", "걸렸다"],
    "keyword": ["미용실", "손님", "많아", "오래", "걸렸다"]
  },
  {
    "index": 343,
    "fullSentence": "물건이 갑자기 늘어서 공간이 부족하다",
    "sentences": ["물건이", "갑자기", "늘어서", "공간이", "부족하다"],
    "keyword": ["물건", "갑자기", "늘어", "공간", "부족하다"]
  },
  {
    "index": 344,
    "fullSentence": "지금 떠나려고 하는데 어디로 가시나요",
    "sentences": ["지금", "떠나려고", "하는데", "어디로", "가시나요"],
    "keyword": ["지금", "떠나려", "하는데", "어디", "가시나요"]
  },
  {
    "index": 345,
    "fullSentence": "갑자기 소리를 질러서 귀가 아팠다",
    "sentences": ["갑자기", "소리를", "질러서", "귀가", "아팠다"],
    "keyword": ["갑자기", "소리", "질러", "귀", "아팠다"]
  },
  {
    "index": 346,
    "fullSentence": "어제 정비소에 오래된 차를 맡겼다",
    "sentences": ["어제", "정비소에", "오래된", "차를", "맡겼다"],
    "keyword": ["어제", "정비소", "오래된", "차", "맡겼다"]
  },
  {
    "index": 347,
    "fullSentence": "아이와 이야기하며 즐거운 시간을 보냈다",
    "sentences": ["아이와", "이야기하며", "즐거운", "시간을", "보냈다"],
    "keyword": ["아이", "이야기하며", "즐거운", "시간", "보냈다"]
  },
  {
    "index": 348,
    "fullSentence": "시합에 도전하여 마지막까지 열심히 하였다",
    "sentences": ["시합에", "도전하여", "마지막까지", "열심히", "하였다"],
    "keyword": ["시합", "도전", "마지막", "열심히", "하였다"]
  },
  {
    "index": 349,
    "fullSentence": "옷을 맞출 때 멋진 장식이 필요해요",
    "sentences": ["옷을", "맞출 때", "멋진", "장식이", "필요해요"],
    "keyword": ["옷", "맞출 때", "멋진", "장식", "필요해요"]
  },
  {
    "index": 350,
    "fullSentence": "회사에 가는 길에 전화를 받았다",
    "sentences": ["회사에", "가는", "길에", "전화를", "받았다"],
    "keyword": ["회사", "가는", "길", "전화", "받았다"]
  },
  {
    "index": 351,
    "fullSentence": "남자가 책을 보면서 노트에 적는다",
    "sentences": ["남자가", "책을", "보면서", "노트에", "적는다"],
    "keyword": ["남자", "책", "보면서", "노트", "적는다"]
  },
  {
    "index": 352,
    "fullSentence": "지갑을 꺼내다 컵을 바닥에 떨어뜨렸다",
    "sentences": ["지갑을", "꺼내다", "컵을", "바닥에", "떨어뜨렸다"],
    "keyword": ["지갑", "꺼내다", "컵", "바닥", "떨어뜨렸다"]
  },
  {
    "index": 353,
    "fullSentence": "오리 가족이 오랫동안 연못을 헤엄쳤다",
    "sentences": ["오리", "가족이", "오랫동안", "연못을", "헤엄쳤다"],
    "keyword": ["오리", "가족", "오랫동안", "연못", "헤엄쳤다"]
  },
  {
    "index": 354,
    "fullSentence": "컴퓨터가 작동이 되지않아 센터를 찾아갔다",
    "sentences": ["컴퓨터가", "작동이", "되지않아", "센터를", "찾아갔다"],
    "keyword": ["컴퓨터", "작동", "되지않아", "센터", "찾아갔다"]
  },
  {
    "index": 355,
    "fullSentence": "오늘은 학교에서 친구와 장난을 쳤다",
    "sentences": ["오늘은", "학교에서", "친구와", "장난을", "쳤다"],
    "keyword": ["오늘", "학교", "친구", "장난", "쳤다"]
  },
  {
    "index": 356,
    "fullSentence": "자동차가 늘어서 주차장이 매우 복잡하다",
    "sentences": ["자동차가", "늘어서", "주차장이", "매우", "복잡하다"],
    "keyword": ["자동차", "늘어", "주차장", "매우", "복잡하다"]
  },
  {
    "index": 357,
    "fullSentence": "마당 가운데 새싹을 심기로 결정했다",
    "sentences": ["마당", "가운데", "새싹을", "심기로", "결정했다"],
    "keyword": ["마당", "가운데", "새싹", "심기", "결정했다"]
  },
  {
    "index": 358,
    "fullSentence": "오늘 점심 한 끼는 이곳에서 먹을까요",
    "sentences": ["오늘", "점심", "한 끼는", "이곳에서", "먹을까요"],
    "keyword": ["오늘", "점심", "한 끼", "이곳", "먹을까요"]
  },
  {
    "index": 359,
    "fullSentence": "많은 아이들을 만나는 것은 즐겁다",
    "sentences": ["많은", "아이들을", "만나는", "것은", "즐겁다"],
    "keyword": ["많은", "아이들", "만나는", "것", "즐겁다"]
  },
  {
    "index": 360,
    "fullSentence": "장소를 둘러보고 사진을 꼼꼼히 찍었다",
    "sentences": ["장소를", "둘러보고", "사진을", "꼼꼼히", "찍었다"],
    "keyword": ["장소", "둘러보고", "사진", "꼼꼼히", "찍었다"]
  }
]
